LICENSE
MANIFEST.in
README.md
requirements.txt
setup.py
PyTLSSniff.egg-info/PKG-INFO
PyTLSSniff.egg-info/SOURCES.txt
PyTLSSniff.egg-info/dependency_links.txt
PyTLSSniff.egg-info/entry_points.txt
PyTLSSniff.egg-info/requires.txt
PyTLSSniff.egg-info/top_level.txt
pytlssniff/__init__.py
pytlssniff/__main__.py
pytlssniff/cli.py
pytlssniff/sniffer.py