Metadata-Version: 2.1
Name: PyTLSSniff
Version: 0.1.3
Summary: Python TLS handshake sniffer to extract domain names
Home-page: https://github.com/DNS-Privacy-Security/PyTLSSniff
Author: M4t7e
License: MIT License
Platform: Any
Classifier: Programming Language :: Python :: 3
Classifier: License :: OSI Approved :: MIT License
Classifier: Operating System :: OS Independent
Requires-Python: >=3.6
